azure/mgmt/onlineexperimentation/__init__.py
azure/mgmt/onlineexperimentation/_client.py
azure/mgmt/onlineexperimentation/_configuration.py
azure/mgmt/onlineexperimentation/_patch.py
azure/mgmt/onlineexperimentation/_version.py
azure/mgmt/onlineexperimentation/py.typed
azure/mgmt/onlineexperimentation/_utils/__init__.py
azure/mgmt/onlineexperimentation/_utils/model_base.py
azure/mgmt/onlineexperimentation/_utils/serialization.py
azure/mgmt/onlineexperimentation/aio/__init__.py
azure/mgmt/onlineexperimentation/aio/_client.py
azure/mgmt/onlineexperimentation/aio/_configuration.py
azure/mgmt/onlineexperimentation/aio/_patch.py
azure/mgmt/onlineexperimentation/aio/operations/__init__.py
azure/mgmt/onlineexperimentation/aio/operations/_operations.py
azure/mgmt/onlineexperimentation/aio/operations/_patch.py
azure/mgmt/onlineexperimentation/models/__init__.py
azure/mgmt/onlineexperimentation/models/_enums.py
azure/mgmt/onlineexperimentation/models/_models.py
azure/mgmt/onlineexperimentation/models/_patch.py
azure/mgmt/onlineexperimentation/operations/__init__.py
azure/mgmt/onlineexperimentation/operations/_operations.py
azure/mgmt/onlineexperimentation/operations/_patch.py
azure_mgmt_onlineexperimentation-1.0.0b1.dist-info/LICENSE
azure_mgmt_onlineexperimentation-1.0.0b1.dist-info/METADATA
azure_mgmt_onlineexperimentation-1.0.0b1.dist-info/WHEEL
azure_mgmt_onlineexperimentation-1.0.0b1.dist-info/top_level.txt
azure_mgmt_onlineexperimentation-1.0.0b1.dist-info/RECORD
